consoleinvaders/__init__.py
consoleinvaders/app.py
consoleinvaders/console.py
consoleinvaders/game.py
consoleinvaders/keyboard.py
consoleinvaders-0.1.dist-info/entry_points.txt
consoleinvaders-0.1.dist-info/LICENSE
consoleinvaders-0.1.dist-info/WHEEL
consoleinvaders-0.1.dist-info/METADATA
consoleinvaders-0.1.dist-info/RECORD
