Metadata-Version: 2.1
Name: consoleinvaders
Version: 0.1
Summary: Space Invaders in your console
Home-page: https://github.com/darthwalsh/ConsoleInvaders
License: UNKNOWN
Author: Carl Walsh
Author-email: carl@carlwa.com
Classifier: License :: OSI Approved :: MIT License
Requires-Dist: pynput >= 1.7.2
Requires-Dist: windows-curses >= 1.0;platform_system=='Windows'
